neatify/__init__.py
neatify/cli.py
neatify/constants.py
neatify/default_extensions.json
neatify/extension_manager.py
neatify/utils.py
neatify-1.0.3.dist-info/METADATA
neatify-1.0.3.dist-info/WHEEL
neatify-1.0.3.dist-info/entry_points.txt
neatify-1.0.3.dist-info/top_level.txt
neatify-1.0.3.dist-info/RECORD
