Metadata-Version: 2.4
Name: neatify
Version: 1.0.3
Summary: A CLI tool to organize files by their extensions
Home-page: https://github.com/anmoljhamb/neatify
Author: Anmol Jhamb
Author-email: Anmol Jhamb <talktoanmol@outlook.com>
License: MIT
Project-URL: Homepage, https://github.com/anmoljhamb/neatify
Classifier: Programming Language :: Python :: 3
Classifier: License :: OSI Approved :: MIT License
Classifier: Operating System :: OS Independent
Requires-Python: >=3.7
Dynamic: author
Dynamic: home-page
Dynamic: requires-python
